mathutils_wuyouran/__init__.py
mathutils_wuyouran/arithmetic.py
mathutils_wuyouran/geometry.py
mathutils_wuyouran/helpers.py
mathutils_wuyouran-0.1.0.dist-info/LICENSE
mathutils_wuyouran-0.1.0.dist-info/METADATA
mathutils_wuyouran-0.1.0.dist-info/WHEEL
mathutils_wuyouran-0.1.0.dist-info/top_level.txt
mathutils_wuyouran-0.1.0.dist-info/RECORD
