Metadata-Version: 2.1
Name: mathutils-wuyouran
Version: 0.1.0
Summary: A simple math utility package with arithmetic and geometry functions
Author: wuyouran
Author-email: 2719875726@qq.com
Classifier: Programming Language :: Python :: 3
Classifier: License :: OSI Approved :: MIT License
Classifier: Operating System :: OS Independent
Requires-Python: >=3.6
License-File: LICENSE
